setup.py
bin/pbdeploy
pbdeploy/__init__.py
pbdeploy/deploy.py
pbdeploy.egg-info/PKG-INFO
pbdeploy.egg-info/SOURCES.txt
pbdeploy.egg-info/dependency_links.txt
pbdeploy.egg-info/requires.txt
pbdeploy.egg-info/top_level.txt